pubsublogger/__init__.py
pubsublogger/exceptions.py
pubsublogger/publisher.py
pubsublogger/subscriber.py
pubsublogger-1.2.7.data/scripts/log_subscriber
pubsublogger-1.2.7.dist-info/LICENSE.txt
pubsublogger-1.2.7.dist-info/METADATA
pubsublogger-1.2.7.dist-info/WHEEL
pubsublogger-1.2.7.dist-info/top_level.txt
pubsublogger-1.2.7.dist-info/RECORD
